<?xml version='1.0' encoding='UTF-8'?>
<tv><channel id="Sportklub.HD.pl">
    <url>http://www.tv.wp.pl</url>
    <display-name lang="pl">Sportklub HD</display-name>
  </channel>
  <channel id="Sportklub.pl">
    <url>http://www.tv.wp.pl</url>
    <display-name lang="pl">Sportklub</display-name>
  </channel>
  <programme channel="Sportklub.HD.pl" start="20251107010000 -0600" stop="20251107032500 -0600">
    <title lang="pl">Men's basketball: Spanish league - match: Baskonia - La Laguna Tenerife</title>
  </programme>
  <programme channel="Sportklub.HD.pl" start="20251107032500 -0600" stop="20251107035000 -0600">
    <title lang="pl">Fifth quarter</title>
    <desc lang="pl">A summary of the most interesting events of the last round in the Spanish basketball league, ACB.</desc>
    <category lang="pl">magazyn sportowy</category>
    <episode-num system="onscreen">E5</episode-num>
  </programme>
  <programme channel="Sportklub.HD.pl" start="20251107035000 -0600" stop="20251107043000 -0600">
    <title lang="pl">World of Freesports</title>
    <desc lang="pl">Short reports from the most interesting events from the world of extreme sports.</desc>
    <category lang="pl">magazyn sportowy</category>
    <episode-num system="onscreen">E44</episode-num>
  </programme>
  <programme channel="Sportklub.HD.pl" start="20251107043000 -0600" stop="20251107053500 -0600">
    <title lang="pl">Pool billiards: Ekstraklasa</title>
  </programme>
  <programme channel="Sportklub.HD.pl" start="20251107053500 -0600" stop="20251107072500 -0600">
    <title lang="pl">Sailing: SailGP in Auckland - Day 1</title>
  </programme>
  <programme channel="Sportklub.HD.pl" start="20251107072500 -0600" stop="20251107074500 -0600">
    <title lang="pl">Fifth quarter</title>
    <desc lang="pl">A summary of the most interesting events of the last round in the Spanish basketball league, ACB.</desc>
    <category lang="pl">magazyn sportowy</category>
    <episode-num system="onscreen">E5</episode-num>
  </programme>
  <programme channel="Sportklub.HD.pl" start="20251107074500 -0600" stop="20251107081500 -0600">
    <title lang="pl">Mass Participation</title>
    <sub-title lang="pl">Cardiff Half Marathon</sub-title>
    <desc lang="pl">Presentation of various forms of mass participation in events such as runs and marathons.The program will include interviews with participants.They will tell you what prompted them to take part in such a challenge.</desc>
    <category lang="pl">magazyn sportowy</category>
    <episode-num system="onscreen">E8</episode-num>
  </programme>
  <programme channel="Sportklub.HD.pl" start="20251107081500 -0600" stop="20251107092000 -0600">
    <title lang="pl">Pool billiards: Ekstraklasa</title>
  </programme>
  <programme channel="Sportklub.HD.pl" start="20251107092000 -0600" stop="20251107103000 -0600">
    <title lang="pl">Pool billiards: Ekstraklasa</title>
  </programme>
  <programme channel="Sportklub.HD.pl" start="20251107103000 -0600" stop="20251107123000 -0600">
    <title lang="pl">Football: Slovenian league - match: NS Mura - Koper FC</title>
  </programme>
  <programme channel="Sportklub.HD.pl" start="20251107123000 -0600" stop="20251107131500 -0600">
    <title lang="pl">World of Freesports</title>
    <desc lang="pl">Short reports from the most interesting events from the world of extreme sports.</desc>
    <category lang="pl">magazyn sportowy</category>
    <episode-num system="onscreen">E44</episode-num>
  </programme>
  <programme channel="Sportklub.HD.pl" start="20251107131500 -0600" stop="20251107151500 -0600">
    <title lang="pl">Football: Slovenian League - match: NK Olimpija Ljubljana - ND Primorje</title>
  </programme>
  <programme channel="Sportklub.HD.pl" start="20251107151500 -0600" stop="20251107162500 -0600">
    <title lang="pl">Equestrian: World Cup competition in Lyon</title>
  </programme>
  <programme channel="Sportklub.HD.pl" start="20251107162500 -0600" stop="20251107164500 -0600">
    <title lang="pl">Fifth quarter</title>
    <desc lang="pl">A summary of the most interesting events of the last round in the Spanish basketball league, ACB.</desc>
    <category lang="pl">magazyn sportowy</category>
    <episode-num system="onscreen">E5</episode-num>
  </programme>
  <programme channel="Sportklub.HD.pl" start="20251107164500 -0600" stop="20251107200000 -0600">
    <title lang="pl">Equestrian: World Cup competition in Lyon</title>
  </programme>
  <programme channel="Sportklub.HD.pl" start="20251107200000 -0600" stop="20251107221000 -0600">
    <title lang="pl">Women's Soccer: National Women's Soccer League - Match: Orlando Pride - Reign</title>
  </programme>
  <programme channel="Sportklub.HD.pl" start="20251107221000 -0600" stop="20251107230000 -0600">
    <title lang="pl">World of Freesports</title>
    <desc lang="pl">Short reports from the most interesting events from the world of extreme sports.</desc>
    <category lang="pl">magazyn sportowy</category>
    <episode-num system="onscreen">E44</episode-num>
  </programme>
  <programme channel="Sportklub.HD.pl" start="20251107230000 -0600" stop="20251108011500 -0600">
    <title lang="pl">Football: Greek League - match: Asteras Gwiazda - OFI</title>
  </programme>
  <programme channel="Sportklub.HD.pl" start="20251108011500 -0600" stop="20251108034500 -0600">
    <title lang="pl">Men's basketball: Spanish league - match: Unicaja - Basquet Girona</title>
  </programme>
  <programme channel="Sportklub.HD.pl" start="20251108034500 -0600" stop="20251108053500 -0600">
    <title lang="pl">Sailing: SailGP in Auckland - Day 2</title>
  </programme>
  <programme channel="Sportklub.HD.pl" start="20251108053500 -0600" stop="20251108064500 -0600">
    <title lang="pl">Pool billiards: Ekstraklasa</title>
  </programme>
  <programme channel="Sportklub.HD.pl" start="20251108064500 -0600" stop="20251108080000 -0600">
    <title lang="pl">Pool billiards: Ekstraklasa</title>
  </programme>
  <programme channel="Sportklub.HD.pl" start="20251108080000 -0600" stop="20251108095500 -0600">
    <title lang="pl">Football: Slovenian league - match: NK Aluminij - NK Domžale</title>
  </programme>
  <programme channel="Sportklub.HD.pl" start="20251108095500 -0600" stop="20251108110000 -0600">
    <title lang="pl">Equestrian: World Cup competition in Lyon</title>
  </programme>
  <programme channel="Sportklub.HD.pl" start="20251108110000 -0600" stop="20251108131500 -0600">
    <title lang="pl">Women's Soccer: National Women's Soccer League - Match: Washington - Racing Louisville</title>
  </programme>
  <programme channel="Sportklub.HD.pl" start="20251108131500 -0600" stop="20251108140000 -0600">
    <title lang="pl">World of Freesports</title>
    <desc lang="pl">Short reports from the most interesting events from the world of extreme sports.</desc>
    <category lang="pl">magazyn sportowy</category>
    <episode-num system="onscreen">E44</episode-num>
  </programme>
  <programme channel="Sportklub.HD.pl" start="20251108140000 -0600" stop="20251108155000 -0600">
    <title lang="pl">Men's basketball: Spanish league - match: MoraBanc Andorra - Unicaja</title>
  </programme>
  <programme channel="Sportklub.HD.pl" start="20251108155000 -0600" stop="20251108180500 -0600">
    <title lang="pl">Football: Greek League - match: Atromitos Halkidonia - Kifisia</title>
  </programme>
  <programme channel="Sportklub.HD.pl" start="20251108180500 -0600" stop="20251108205500 -0600">
    <title lang="pl">Men's basketball: Spanish league - match: Baskonia - La Laguna Tenerife</title>
  </programme>
  <programme channel="Sportklub.HD.pl" start="20251108205500 -0600" stop="20251108230000 -0600">
    <title lang="pl">Sailing: SailGP in Auckland - Day 1</title>
  </programme>
  <programme channel="Sportklub.HD.pl" start="20251108230000 -0600" stop="20251109020000 -0600">
    <title lang="pl">Equestrian: World Cup competition in Lyon</title>
  </programme>
  <programme channel="Sportklub.HD.pl" start="20251109020000 -0600" stop="20251109035500 -0600">
    <title lang="pl">Sailing: SailGP in Auckland - Day 1</title>
  </programme>
  <programme channel="Sportklub.HD.pl" start="20251109035500 -0600" stop="20251109041500 -0600">
    <title lang="pl">Fifth quarter</title>
    <desc lang="pl">A summary of the most interesting events of the last round in the Spanish basketball league, ACB.</desc>
    <category lang="pl">magazyn sportowy</category>
    <episode-num system="onscreen">E5</episode-num>
  </programme>
  <programme channel="Sportklub.HD.pl" start="20251109041500 -0600" stop="20251109053000 -0600">
    <title lang="pl">Pool billiards: Ekstraklasa</title>
  </programme>
  <programme channel="Sportklub.HD.pl" start="20251109053000 -0600" stop="20251109072000 -0600">
    <title lang="pl">Men's basketball: Spanish league - match: Basquet Girona - Barça</title>
  </programme>
  <programme channel="Sportklub.HD.pl" start="20251109072000 -0600" stop="20251109074500 -0600">
    <title lang="pl">World of Freesports</title>
    <desc lang="pl">Short reports from the most interesting events from the world of extreme sports.</desc>
    <category lang="pl">magazyn sportowy</category>
    <episode-num system="onscreen">E45</episode-num>
  </programme>
  <programme channel="Sportklub.HD.pl" start="20251109074500 -0600" stop="20251109103500 -0600">
    <title lang="pl">Equestrian: World Cup competition in Verona</title>
  </programme>
  <programme channel="Sportklub.HD.pl" start="20251109103500 -0600" stop="20251109113000 -0600">
    <title lang="pl">Pool billiards: Ekstraklasa</title>
  </programme>
  <programme channel="Sportklub.HD.pl" start="20251109113000 -0600" stop="20251109140000 -0600">
    <title lang="pl">Women's soccer: National Women's Soccer League - match: Kansas City - Gotham</title>
  </programme>
  <programme channel="Sportklub.HD.pl" start="20251109140000 -0600" stop="20251109161000 -0600">
    <title lang="pl">Women's Soccer: National Women's Soccer League - Match: Portland Thorns - San Diego Wave</title>
  </programme>
  <programme channel="Sportklub.HD.pl" start="20251109161000 -0600" stop="20251109182000 -0600">
    <title lang="pl">Men's basketball: Spanish league - match: Joventut Badalona - Real Madrid</title>
  </programme>
  <programme channel="Sportklub.HD.pl" start="20251109182000 -0600" stop="20251109205500 -0600">
    <title lang="pl">Football: Greek League - match: Levadeiakos FC - Panserraikos</title>
  </programme>
  <programme channel="Sportklub.HD.pl" start="20251109205500 -0600" stop="20251109230000 -0600">
    <title lang="pl">Sailing: SailGP in Auckland - Day 2</title>
  </programme>
  <programme channel="Sportklub.HD.pl" start="20251109230000 -0600" stop="20251110010500 -0600">
    <title lang="pl">Men's basketball: Spanish league - match: Basquet Girona - Barça</title>
  </programme>
  <programme channel="Sportklub.HD.pl" start="20251110010500 -0600" stop="20251110031500 -0600">
    <title lang="pl">Football: Greek League - match: Levadeiakos FC - Panserraikos</title>
  </programme>
  <programme channel="Sportklub.HD.pl" start="20251110031500 -0600" stop="20251110045500 -0600">
    <title lang="pl">Sailing: SailGP in Auckland - Day 2</title>
  </programme>
  <programme channel="Sportklub.HD.pl" start="20251110045500 -0600" stop="20251110071500 -0600">
    <title lang="pl">Men's basketball: Spanish league - match: Casademont Zaragoza - Real Madrid</title>
  </programme>
  <programme channel="Sportklub.HD.pl" start="20251110071500 -0600" stop="20251110090000 -0600">
    <title lang="pl">Sailing: SailGP in Auckland - Day 1</title>
  </programme>
  <programme channel="Sportklub.HD.pl" start="20251110090000 -0600" stop="20251110120500 -0600">
    <title lang="pl">Equestrian: World Cup competition in Verona</title>
  </programme>
  <programme channel="Sportklub.HD.pl" start="20251110120500 -0600" stop="20251110141500 -0600">
    <title lang="pl">Football: Greek League - match: Panserraikos - PAOK FC</title>
  </programme>
  <programme channel="Sportklub.HD.pl" start="20251110141500 -0600" stop="20251110162000 -0600">
    <title lang="pl">Men's basketball: Spanish league - match: MoraBanc Andorra - Unicaja</title>
  </programme>
  <programme channel="Sportklub.HD.pl" start="20251110162000 -0600" stop="20251110184000 -0600">
    <title lang="pl">Football: Greek League - match: Asteras Gwiazda - OFI</title>
  </programme>
  <programme channel="Sportklub.HD.pl" start="20251110184000 -0600" stop="20251110213500 -0600">
    <title lang="pl">Men's basketball: Spanish league - match: Baskonia - La Laguna Tenerife</title>
  </programme>
  <programme channel="Sportklub.HD.pl" start="20251110213500 -0600" stop="20251110220000 -0600">
    <title lang="pl">World of Freesports</title>
    <desc lang="pl">Short reports from the most interesting events from the world of extreme sports.</desc>
    <category lang="pl">magazyn sportowy</category>
    <episode-num system="onscreen">E45</episode-num>
  </programme>
  <programme channel="Sportklub.HD.pl" start="20251110220000 -0600" stop="20251110230000 -0600">
    <title lang="pl">Equestrian: World Cup competition in Lyon</title>
  </programme>
  <programme channel="Sportklub.HD.pl" start="20251110230000 -0600" stop="20251111010000 -0600">
    <title lang="pl">Men's Basketball: Spanish League</title>
  </programme>
  <programme channel="Sportklub.HD.pl" start="20251111010000 -0600" stop="20251111030500 -0600">
    <title lang="pl">Men's Basketball: Spanish League</title>
  </programme>
  <programme channel="Sportklub.HD.pl" start="20251111030500 -0600" stop="20251111034000 -0600">
    <title lang="pl">Motorsport</title>
    <category lang="pl">magazyn sportów motorowych</category>
  </programme>
  <programme channel="Sportklub.HD.pl" start="20251111034000 -0600" stop="20251111053500 -0600">
    <title lang="pl">Football: Slovenian league</title>
  </programme>
  <programme channel="Sportklub.HD.pl" start="20251111053500 -0600" stop="20251111073000 -0600">
    <title lang="pl">Football: Slovenian league</title>
  </programme>
  <programme channel="Sportklub.HD.pl" start="20251111073000 -0600" stop="20251111080500 -0600">
    <title lang="pl">Motorsport</title>
    <category lang="pl">magazyn sportów motorowych</category>
  </programme>
  <programme channel="Sportklub.HD.pl" start="20251111080500 -0600" stop="20251111092000 -0600">
    <title lang="pl">Multisport</title>
    <category lang="pl">magazyn sportowy</category>
  </programme>
  <programme channel="Sportklub.HD.pl" start="20251111092000 -0600" stop="20251111113000 -0600">
    <title lang="pl">Men's Basketball: Spanish League</title>
  </programme>
  <programme channel="Sportklub.HD.pl" start="20251111113000 -0600" stop="20251111133500 -0600">
    <title lang="pl">Football: Greek League</title>
  </programme>
  <programme channel="Sportklub.HD.pl" start="20251111133500 -0600" stop="20251111154500 -0600">
    <title lang="pl">Football: Greek League</title>
  </programme>
  <programme channel="Sportklub.HD.pl" start="20251111154500 -0600" stop="20251111175000 -0600">
    <title lang="pl">Football: Slovenian league</title>
  </programme>
  <programme channel="Sportklub.HD.pl" start="20251111175000 -0600" stop="20251111190500 -0600">
    <title lang="pl">Multisport</title>
    <category lang="pl">magazyn sportowy</category>
  </programme>
  <programme channel="Sportklub.HD.pl" start="20251111190500 -0600" stop="20251111200000 -0600">
    <title lang="pl">Motorsport</title>
    <category lang="pl">magazyn sportów motorowych</category>
  </programme>
  <programme channel="Sportklub.HD.pl" start="20251111200000 -0600" stop="20251111221500 -0600">
    <title lang="pl">Football: Greek League</title>
  </programme>
  <programme channel="Sportklub.HD.pl" start="20251111221500 -0600" stop="20251111230000 -0600">
    <title lang="pl">Motorsport</title>
    <category lang="pl">magazyn sportów motorowych</category>
  </programme>
  <programme channel="Sportklub.HD.pl" start="20251111230000 -0600" stop="20251112010000 -0600">
    <title lang="pl">Men's Basketball: Spanish League</title>
  </programme>
  <programme channel="Sportklub.pl" start="20251107010000 -0600" stop="20251107032500 -0600">
    <title lang="pl">Men's basketball: Spanish league - match: Baskonia - La Laguna Tenerife</title>
  </programme>
  <programme channel="Sportklub.pl" start="20251107032500 -0600" stop="20251107035000 -0600">
    <title lang="pl">Fifth quarter</title>
    <desc lang="pl">A summary of the most interesting events of the last round in the Spanish basketball league, ACB.</desc>
    <category lang="pl">magazyn sportowy</category>
    <episode-num system="onscreen">E5</episode-num>
  </programme>
  <programme channel="Sportklub.pl" start="20251107035000 -0600" stop="20251107043000 -0600">
    <title lang="pl">World of Freesports</title>
    <desc lang="pl">Short reports from the most interesting events from the world of extreme sports.</desc>
    <category lang="pl">magazyn sportowy</category>
    <episode-num system="onscreen">E44</episode-num>
  </programme>
  <programme channel="Sportklub.pl" start="20251107043000 -0600" stop="20251107053500 -0600">
    <title lang="pl">Pool billiards: Ekstraklasa</title>
  </programme>
  <programme channel="Sportklub.pl" start="20251107053500 -0600" stop="20251107072500 -0600">
    <title lang="pl">Sailing: SailGP in Auckland - Day 1</title>
  </programme>
  <programme channel="Sportklub.pl" start="20251107072500 -0600" stop="20251107074500 -0600">
    <title lang="pl">Fifth quarter</title>
    <desc lang="pl">A summary of the most interesting events of the last round in the Spanish basketball league, ACB.</desc>
    <category lang="pl">magazyn sportowy</category>
    <episode-num system="onscreen">E5</episode-num>
  </programme>
  <programme channel="Sportklub.pl" start="20251107074500 -0600" stop="20251107081000 -0600">
    <title lang="pl">Mass Participation</title>
    <sub-title lang="pl">Cardiff Half Marathon</sub-title>
    <desc lang="pl">Presentation of various forms of mass participation in events such as runs and marathons.The program will include interviews with participants.They will tell you what prompted them to take part in such a challenge.</desc>
    <category lang="pl">magazyn sportowy</category>
    <episode-num system="onscreen">E8</episode-num>
  </programme>
  <programme channel="Sportklub.pl" start="20251107081000 -0600" stop="20251107091500 -0600">
    <title lang="pl">Pool billiards: Ekstraklasa</title>
  </programme>
  <programme channel="Sportklub.pl" start="20251107091500 -0600" stop="20251107103000 -0600">
    <title lang="pl">Pool billiards: Ekstraklasa</title>
  </programme>
  <programme channel="Sportklub.pl" start="20251107103000 -0600" stop="20251107123500 -0600">
    <title lang="pl">Football: Slovenian league - match: NS Mura - Koper FC</title>
  </programme>
  <programme channel="Sportklub.pl" start="20251107123500 -0600" stop="20251107131500 -0600">
    <title lang="pl">World of Freesports</title>
    <desc lang="pl">Short reports from the most interesting events from the world of extreme sports.</desc>
    <category lang="pl">magazyn sportowy</category>
    <episode-num system="onscreen">E44</episode-num>
  </programme>
  <programme channel="Sportklub.pl" start="20251107131500 -0600" stop="20251107151500 -0600">
    <title lang="pl">Football: Slovenian League - match: NK Olimpija Ljubljana - ND Primorje</title>
  </programme>
  <programme channel="Sportklub.pl" start="20251107151500 -0600" stop="20251107162500 -0600">
    <title lang="pl">Equestrian: World Cup competition in Lyon</title>
  </programme>
  <programme channel="Sportklub.pl" start="20251107162500 -0600" stop="20251107164500 -0600">
    <title lang="pl">Fifth quarter</title>
    <desc lang="pl">A summary of the most interesting events of the last round in the Spanish basketball league, ACB.</desc>
    <category lang="pl">magazyn sportowy</category>
    <episode-num system="onscreen">E5</episode-num>
  </programme>
  <programme channel="Sportklub.pl" start="20251107164500 -0600" stop="20251107200000 -0600">
    <title lang="pl">Equestrian: World Cup competition in Lyon</title>
  </programme>
  <programme channel="Sportklub.pl" start="20251107200000 -0600" stop="20251107221000 -0600">
    <title lang="pl">Women's Soccer: National Women's Soccer League - Match: Orlando Pride - Reign</title>
  </programme>
  <programme channel="Sportklub.pl" start="20251107221000 -0600" stop="20251107230000 -0600">
    <title lang="pl">World of Freesports</title>
    <desc lang="pl">Short reports from the most interesting events from the world of extreme sports.</desc>
    <category lang="pl">magazyn sportowy</category>
    <episode-num system="onscreen">E44</episode-num>
  </programme>
  <programme channel="Sportklub.pl" start="20251107230000 -0600" stop="20251108010000 -0600">
    <title lang="pl">Men's Basketball: Spanish League</title>
  </programme>
  <programme channel="Sportklub.pl" start="20251108010000 -0600" stop="20251108030500 -0600">
    <title lang="pl">Men's Basketball: Spanish League</title>
  </programme>
  <programme channel="Sportklub.pl" start="20251108030500 -0600" stop="20251108034000 -0600">
    <title lang="pl">Motorsport</title>
    <category lang="pl">magazyn sportów motorowych</category>
  </programme>
  <programme channel="Sportklub.pl" start="20251108034000 -0600" stop="20251108053500 -0600">
    <title lang="pl">Football: Slovenian league</title>
  </programme>
  <programme channel="Sportklub.pl" start="20251108053500 -0600" stop="20251108073000 -0600">
    <title lang="pl">Football: Slovenian league</title>
  </programme>
  <programme channel="Sportklub.pl" start="20251108073000 -0600" stop="20251108080500 -0600">
    <title lang="pl">Motorsport</title>
    <category lang="pl">magazyn sportów motorowych</category>
  </programme>
  <programme channel="Sportklub.pl" start="20251108080500 -0600" stop="20251108092000 -0600">
    <title lang="pl">Multisport</title>
    <category lang="pl">magazyn sportowy</category>
  </programme>
  <programme channel="Sportklub.pl" start="20251108092000 -0600" stop="20251108113000 -0600">
    <title lang="pl">Men's Basketball: Spanish League</title>
  </programme>
  <programme channel="Sportklub.pl" start="20251108113000 -0600" stop="20251108133500 -0600">
    <title lang="pl">Football: Greek League</title>
  </programme>
  <programme channel="Sportklub.pl" start="20251108133500 -0600" stop="20251108154500 -0600">
    <title lang="pl">Football: Greek League</title>
  </programme>
  <programme channel="Sportklub.pl" start="20251108154500 -0600" stop="20251108175000 -0600">
    <title lang="pl">Football: Slovenian league</title>
  </programme>
  <programme channel="Sportklub.pl" start="20251108175000 -0600" stop="20251108190500 -0600">
    <title lang="pl">Multisport</title>
    <category lang="pl">magazyn sportowy</category>
  </programme>
  <programme channel="Sportklub.pl" start="20251108190500 -0600" stop="20251108200000 -0600">
    <title lang="pl">Motorsport</title>
    <category lang="pl">magazyn sportów motorowych</category>
  </programme>
  <programme channel="Sportklub.pl" start="20251108200000 -0600" stop="20251108221500 -0600">
    <title lang="pl">Football: Greek League</title>
  </programme>
  <programme channel="Sportklub.pl" start="20251108221500 -0600" stop="20251108230000 -0600">
    <title lang="pl">Motorsport</title>
    <category lang="pl">magazyn sportów motorowych</category>
  </programme>
  <programme channel="Sportklub.pl" start="20251108230000 -0600" stop="20251109010000 -0600">
    <title lang="pl">Men's Basketball: Spanish League</title>
  </programme>
  <programme channel="Sportklub.pl" start="20251109010000 -0600" stop="20251109030500 -0600">
    <title lang="pl">Men's Basketball: Spanish League</title>
  </programme>
  <programme channel="Sportklub.pl" start="20251109030500 -0600" stop="20251109034000 -0600">
    <title lang="pl">Motorsport</title>
    <category lang="pl">magazyn sportów motorowych</category>
  </programme>
  <programme channel="Sportklub.pl" start="20251109034000 -0600" stop="20251109053500 -0600">
    <title lang="pl">Football: Slovenian league</title>
  </programme>
  <programme channel="Sportklub.pl" start="20251109053500 -0600" stop="20251109073000 -0600">
    <title lang="pl">Football: Slovenian league</title>
  </programme>
  <programme channel="Sportklub.pl" start="20251109073000 -0600" stop="20251109080500 -0600">
    <title lang="pl">Motorsport</title>
    <category lang="pl">magazyn sportów motorowych</category>
  </programme>
  <programme channel="Sportklub.pl" start="20251109080500 -0600" stop="20251109092000 -0600">
    <title lang="pl">Multisport</title>
    <category lang="pl">magazyn sportowy</category>
  </programme>
  <programme channel="Sportklub.pl" start="20251109092000 -0600" stop="20251109113000 -0600">
    <title lang="pl">Men's Basketball: Spanish League</title>
  </programme>
  <programme channel="Sportklub.pl" start="20251109113000 -0600" stop="20251109133500 -0600">
    <title lang="pl">Football: Greek League</title>
  </programme>
  <programme channel="Sportklub.pl" start="20251109133500 -0600" stop="20251109154500 -0600">
    <title lang="pl">Football: Greek League</title>
  </programme>
  <programme channel="Sportklub.pl" start="20251109154500 -0600" stop="20251109175000 -0600">
    <title lang="pl">Football: Slovenian league</title>
  </programme>
  <programme channel="Sportklub.pl" start="20251109175000 -0600" stop="20251109190500 -0600">
    <title lang="pl">Multisport</title>
    <category lang="pl">magazyn sportowy</category>
  </programme>
  <programme channel="Sportklub.pl" start="20251109190500 -0600" stop="20251109200000 -0600">
    <title lang="pl">Motorsport</title>
    <category lang="pl">magazyn sportów motorowych</category>
  </programme>
  <programme channel="Sportklub.pl" start="20251109200000 -0600" stop="20251109221500 -0600">
    <title lang="pl">Football: Greek League</title>
  </programme>
  <programme channel="Sportklub.pl" start="20251109221500 -0600" stop="20251109230000 -0600">
    <title lang="pl">Motorsport</title>
    <category lang="pl">magazyn sportów motorowych</category>
  </programme>
  <programme channel="Sportklub.pl" start="20251109230000 -0600" stop="20251110010000 -0600">
    <title lang="pl">Men's Basketball: Spanish League</title>
  </programme>
  <programme channel="Sportklub.pl" start="20251110010000 -0600" stop="20251110030500 -0600">
    <title lang="pl">Men's Basketball: Spanish League</title>
  </programme>
  <programme channel="Sportklub.pl" start="20251110030500 -0600" stop="20251110034000 -0600">
    <title lang="pl">Motorsport</title>
    <category lang="pl">magazyn sportów motorowych</category>
  </programme>
  <programme channel="Sportklub.pl" start="20251110034000 -0600" stop="20251110053500 -0600">
    <title lang="pl">Football: Slovenian league</title>
  </programme>
  <programme channel="Sportklub.pl" start="20251110053500 -0600" stop="20251110073000 -0600">
    <title lang="pl">Football: Slovenian league</title>
  </programme>
  <programme channel="Sportklub.pl" start="20251110073000 -0600" stop="20251110080500 -0600">
    <title lang="pl">Motorsport</title>
    <category lang="pl">magazyn sportów motorowych</category>
  </programme>
  <programme channel="Sportklub.pl" start="20251110080500 -0600" stop="20251110092000 -0600">
    <title lang="pl">Multisport</title>
    <category lang="pl">magazyn sportowy</category>
  </programme>
  <programme channel="Sportklub.pl" start="20251110092000 -0600" stop="20251110113000 -0600">
    <title lang="pl">Men's Basketball: Spanish League</title>
  </programme>
  <programme channel="Sportklub.pl" start="20251110113000 -0600" stop="20251110133500 -0600">
    <title lang="pl">Football: Greek League</title>
  </programme>
  <programme channel="Sportklub.pl" start="20251110133500 -0600" stop="20251110154500 -0600">
    <title lang="pl">Football: Greek League</title>
  </programme>
  <programme channel="Sportklub.pl" start="20251110154500 -0600" stop="20251110175000 -0600">
    <title lang="pl">Football: Slovenian league</title>
  </programme>
  <programme channel="Sportklub.pl" start="20251110175000 -0600" stop="20251110190500 -0600">
    <title lang="pl">Multisport</title>
    <category lang="pl">magazyn sportowy</category>
  </programme>
  <programme channel="Sportklub.pl" start="20251110190500 -0600" stop="20251110200000 -0600">
    <title lang="pl">Motorsport</title>
    <category lang="pl">magazyn sportów motorowych</category>
  </programme>
  <programme channel="Sportklub.pl" start="20251110200000 -0600" stop="20251110221500 -0600">
    <title lang="pl">Football: Greek League</title>
  </programme>
  <programme channel="Sportklub.pl" start="20251110221500 -0600" stop="20251110230000 -0600">
    <title lang="pl">Motorsport</title>
    <category lang="pl">magazyn sportów motorowych</category>
  </programme>
  <programme channel="Sportklub.pl" start="20251110230000 -0600" stop="20251111010000 -0600">
    <title lang="pl">Men's Basketball: Spanish League</title>
  </programme>
  <programme channel="Sportklub.pl" start="20251111010000 -0600" stop="20251111030500 -0600">
    <title lang="pl">Men's Basketball: Spanish League</title>
  </programme>
  <programme channel="Sportklub.pl" start="20251111030500 -0600" stop="20251111034000 -0600">
    <title lang="pl">Motorsport</title>
    <category lang="pl">magazyn sportów motorowych</category>
  </programme>
  <programme channel="Sportklub.pl" start="20251111034000 -0600" stop="20251111053500 -0600">
    <title lang="pl">Football: Slovenian league</title>
  </programme>
  <programme channel="Sportklub.pl" start="20251111053500 -0600" stop="20251111073000 -0600">
    <title lang="pl">Football: Slovenian league</title>
  </programme>
  <programme channel="Sportklub.pl" start="20251111073000 -0600" stop="20251111080500 -0600">
    <title lang="pl">Motorsport</title>
    <category lang="pl">magazyn sportów motorowych</category>
  </programme>
  <programme channel="Sportklub.pl" start="20251111080500 -0600" stop="20251111092000 -0600">
    <title lang="pl">Multisport</title>
    <category lang="pl">magazyn sportowy</category>
  </programme>
  <programme channel="Sportklub.pl" start="20251111092000 -0600" stop="20251111113000 -0600">
    <title lang="pl">Men's Basketball: Spanish League</title>
  </programme>
  <programme channel="Sportklub.pl" start="20251111113000 -0600" stop="20251111133500 -0600">
    <title lang="pl">Football: Greek League</title>
  </programme>
  <programme channel="Sportklub.pl" start="20251111133500 -0600" stop="20251111154500 -0600">
    <title lang="pl">Football: Greek League</title>
  </programme>
  <programme channel="Sportklub.pl" start="20251111154500 -0600" stop="20251111175000 -0600">
    <title lang="pl">Football: Slovenian league</title>
  </programme>
  <programme channel="Sportklub.pl" start="20251111175000 -0600" stop="20251111190500 -0600">
    <title lang="pl">Multisport</title>
    <category lang="pl">magazyn sportowy</category>
  </programme>
  <programme channel="Sportklub.pl" start="20251111190500 -0600" stop="20251111200000 -0600">
    <title lang="pl">Motorsport</title>
    <category lang="pl">magazyn sportów motorowych</category>
  </programme>
  <programme channel="Sportklub.pl" start="20251111200000 -0600" stop="20251111221500 -0600">
    <title lang="pl">Football: Greek League</title>
  </programme>
  <programme channel="Sportklub.pl" start="20251111221500 -0600" stop="20251111230000 -0600">
    <title lang="pl">Motorsport</title>
    <category lang="pl">magazyn sportów motorowych</category>
  </programme>
  <programme channel="Sportklub.pl" start="20251111230000 -0600" stop="20251112010000 -0600">
    <title lang="pl">Men's Basketball: Spanish League</title>
  </programme>
  </tv>