<?xml version='1.0' encoding='UTF-8'?>
<tv><channel id="Sportklub.HD.pl">
    <url>http://www.tv.wp.pl</url>
    <display-name lang="pl">Sportklub HD</display-name>
  </channel>
  <channel id="Sportklub.pl">
    <url>http://www.tv.wp.pl</url>
    <display-name lang="pl">Sportklub</display-name>
  </channel>
  <programme channel="Sportklub.HD.pl" start="20251124011500 -0600" stop="20251124035500 -0600">
    <title lang="pl">Men's basketball: Spanish League - match: Casademont Zaragoza - Unicaja Malaga</title>
  </programme>
  <programme channel="Sportklub.HD.pl" start="20251124035500 -0600" stop="20251124061500 -0600">
    <title lang="pl">Football: Slovenian league - match: FC Koper - NK Aluminij</title>
  </programme>
  <programme channel="Sportklub.HD.pl" start="20251124061500 -0600" stop="20251124092000 -0600">
    <title lang="pl">Equestrian: World Cup competitions in Stuttgart</title>
  </programme>
  <programme channel="Sportklub.HD.pl" start="20251124092000 -0600" stop="20251124103000 -0600">
    <title lang="pl">Equestrian: World Cup competitions in Stuttgart - summary</title>
  </programme>
  <programme channel="Sportklub.HD.pl" start="20251124103000 -0600" stop="20251124123000 -0600">
    <title lang="pl">Football: Slovenian league - match: NK Bravo - NK Radomlje</title>
  </programme>
  <programme channel="Sportklub.HD.pl" start="20251124123000 -0600" stop="20251124144000 -0600">
    <title lang="pl">Men's basketball: Spanish league - match: Barca - Cazoo Baskonia Vitoria-Gasteiz</title>
  </programme>
  <programme channel="Sportklub.HD.pl" start="20251124144000 -0600" stop="20251124164500 -0600">
    <title lang="pl">Football: Slovenian league - match: NK Domzale - NK Celje</title>
  </programme>
  <programme channel="Sportklub.HD.pl" start="20251124164500 -0600" stop="20251124193000 -0600">
    <title lang="pl">Men's basketball: Spanish league - match: Unicaja Malaga - BAXI Manresa</title>
  </programme>
  <programme channel="Sportklub.HD.pl" start="20251124193000 -0600" stop="20251124222500 -0600">
    <title lang="pl">Women's soccer: National Women's Soccer League - final match: Washington Spirit - Gotham FC</title>
  </programme>
  <programme channel="Sportklub.HD.pl" start="20251124222500 -0600" stop="20251124230000 -0600">
    <title lang="pl">GWA Wingfoil World Tour</title>
    <category lang="pl">magazyn sportowy</category>
  </programme>
  <programme channel="Sportklub.HD.pl" start="20251124230000 -0600" stop="20251125013000 -0600">
    <title lang="pl">Men's basketball: Spanish league - match: Cazoo Baskonia Vitoria-Gasteiz - Surne Bilbao Basket</title>
  </programme>
  <programme channel="Sportklub.HD.pl" start="20251125013000 -0600" stop="20251125034000 -0600">
    <title lang="pl">Football: Greek League - match: Asteras Tripolis - Panetolikos GFS</title>
  </programme>
  <programme channel="Sportklub.HD.pl" start="20251125034000 -0600" stop="20251125054500 -0600">
    <title lang="pl">Football: Slovenian League - match: NK Maribor - NK Olimpija Ljubljana</title>
  </programme>
  <programme channel="Sportklub.HD.pl" start="20251125054500 -0600" stop="20251125080000 -0600">
    <title lang="pl">Men's basketball: Spanish league - match: CB Gran Canaria - Barca</title>
  </programme>
  <programme channel="Sportklub.HD.pl" start="20251125080000 -0600" stop="20251125101500 -0600">
    <title lang="pl">Football: Greek League - match: MGS Panserraikos - Panathinaikos AO</title>
  </programme>
  <programme channel="Sportklub.HD.pl" start="20251125101500 -0600" stop="20251125121500 -0600">
    <title lang="pl">Football: Slovenian league - match: FC Koper - NK Aluminij</title>
  </programme>
  <programme channel="Sportklub.HD.pl" start="20251125121500 -0600" stop="20251125124000 -0600">
    <title lang="pl">Fifth quarter</title>
    <desc lang="pl">A summary of the most interesting events of the last round in the Spanish basketball league, ACB.</desc>
    <category lang="pl">magazyn sportowy</category>
  </programme>
  <programme channel="Sportklub.HD.pl" start="20251125124000 -0600" stop="20251125153500 -0600">
    <title lang="pl">Equestrian: World Cup competitions in Stuttgart</title>
  </programme>
  <programme channel="Sportklub.HD.pl" start="20251125153500 -0600" stop="20251125170000 -0600">
    <title lang="pl">Women's volleyball: Slovenian league - match: OTP Banka Branik Maribor - OK Formis</title>
  </programme>
  <programme channel="Sportklub.HD.pl" start="20251125170000 -0600" stop="20251125192000 -0600">
    <title lang="pl">Men's basketball: Spanish league - match: Barca - Cazoo Baskonia Vitoria-Gasteiz</title>
  </programme>
  <programme channel="Sportklub.HD.pl" start="20251125192000 -0600" stop="20251125213000 -0600">
    <title lang="pl">Football: Slovenian league - match: NK Domzale - NK Celje</title>
  </programme>
  <programme channel="Sportklub.HD.pl" start="20251125213000 -0600" stop="20251125230000 -0600">
    <title lang="pl">Equestrian: World Cup competitions in Oslo - summary</title>
  </programme>
  <programme channel="Sportklub.HD.pl" start="20251125230000 -0600" stop="20251126013500 -0600">
    <title lang="pl">Men's basketball: Spanish league - match: Cazoo Baskonia Vitoria-Gasteiz - Surne Bilbao Basket</title>
  </programme>
  <programme channel="Sportklub.HD.pl" start="20251126013500 -0600" stop="20251126034500 -0600">
    <title lang="pl">Football: Greek League - match: MGS Panserraikos - Panathinaikos AO</title>
  </programme>
  <programme channel="Sportklub.HD.pl" start="20251126034500 -0600" stop="20251126060000 -0600">
    <title lang="pl">Football: Slovenian league - match: FC Koper - NK Aluminij</title>
  </programme>
  <programme channel="Sportklub.HD.pl" start="20251126060000 -0600" stop="20251126083000 -0600">
    <title lang="pl">Men's basketball: Spanish league - match: Unicaja Malaga - BAXI Manresa</title>
  </programme>
  <programme channel="Sportklub.HD.pl" start="20251126083000 -0600" stop="20251126103500 -0600">
    <title lang="pl">Football: Greek League - match: PAOK FC - AE Kifisia</title>
  </programme>
  <programme channel="Sportklub.HD.pl" start="20251126103500 -0600" stop="20251126123000 -0600">
    <title lang="pl">Football: Slovenian league - match: NK Domzale - NK Celje</title>
  </programme>
  <programme channel="Sportklub.HD.pl" start="20251126123000 -0600" stop="20251126124500 -0600">
    <title lang="pl">Fifth quarter</title>
    <desc lang="pl">A summary of the most interesting events of the last round in the Spanish basketball league, ACB.</desc>
    <category lang="pl">magazyn sportowy</category>
  </programme>
  <programme channel="Sportklub.HD.pl" start="20251126124500 -0600" stop="20251126151000 -0600">
    <title lang="pl">Men's basketball: Spanish league - match: Barca - Cazoo Baskonia Vitoria-Gasteiz</title>
  </programme>
  <programme channel="Sportklub.HD.pl" start="20251126151000 -0600" stop="20251126172000 -0600">
    <title lang="pl">Football: Slovenian League - match: NK Maribor - NK Olimpija Ljubljana</title>
  </programme>
  <programme channel="Sportklub.HD.pl" start="20251126172000 -0600" stop="20251126204000 -0600">
    <title lang="pl">Equestrian: World Cup competitions in Stuttgart</title>
  </programme>
  <programme channel="Sportklub.HD.pl" start="20251126204000 -0600" stop="20251126230000 -0600">
    <title lang="pl">Women's volleyball: Slovenian league - match: OTP Banka Branik Maribor - OK Formis</title>
  </programme>
  <programme channel="Sportklub.HD.pl" start="20251126230000 -0600" stop="20251127020000 -0600">
    <title lang="pl">Equestrian: World Cup competitions in Stuttgart</title>
  </programme>
  <programme channel="Sportklub.HD.pl" start="20251127020000 -0600" stop="20251127040500 -0600">
    <title lang="pl">Football: Slovenian league - match: NK Domzale - NK Celje</title>
  </programme>
  <programme channel="Sportklub.HD.pl" start="20251127040500 -0600" stop="20251127061500 -0600">
    <title lang="pl">Women's soccer: National Women's Soccer League - final match</title>
  </programme>
  <programme channel="Sportklub.HD.pl" start="20251127061500 -0600" stop="20251127082500 -0600">
    <title lang="pl">Men's basketball: Spanish league - match: Unicaja Malaga - BAXI Manresa</title>
  </programme>
  <programme channel="Sportklub.HD.pl" start="20251127082500 -0600" stop="20251127104000 -0600">
    <title lang="pl">Football: Greek League - match: MGS Panserraikos - Panathinaikos AO</title>
  </programme>
  <programme channel="Sportklub.HD.pl" start="20251127104000 -0600" stop="20251127130000 -0600">
    <title lang="pl">Women's volleyball: Slovenian league - match: OTP Banka Branik Maribor - OK Formis</title>
  </programme>
  <programme channel="Sportklub.HD.pl" start="20251127130000 -0600" stop="20251127151500 -0600">
    <title lang="pl">Football: Slovenian league - match: NK Bravo - NK Radomlje</title>
  </programme>
  <programme channel="Sportklub.HD.pl" start="20251127151500 -0600" stop="20251127173500 -0600">
    <title lang="pl">Football: Greek League - match: PAOK FC - AE Kifisia</title>
  </programme>
  <programme channel="Sportklub.HD.pl" start="20251127173500 -0600" stop="20251127195000 -0600">
    <title lang="pl">Men's basketball: Spanish league - match: Valencia Basket - La Laguna Tenerife</title>
  </programme>
  <programme channel="Sportklub.HD.pl" start="20251127195000 -0600" stop="20251127220500 -0600">
    <title lang="pl">Football: Slovenian league - match: FC Koper - NK Aluminij</title>
  </programme>
  <programme channel="Sportklub.HD.pl" start="20251127220500 -0600" stop="20251127230000 -0600">
    <title lang="pl">World of Freesports</title>
    <desc lang="pl">Short reports from the most interesting events from the world of extreme sports.</desc>
    <category lang="pl">magazyn sportowy</category>
  </programme>
  <programme channel="Sportklub.HD.pl" start="20251127230000 -0600" stop="20251128010500 -0600">
    <title lang="pl">Men's basketball: Spanish league - match: CB Gran Canaria - Barca</title>
  </programme>
  <programme channel="Sportklub.HD.pl" start="20251128010500 -0600" stop="20251128030500 -0600">
    <title lang="pl">Football: Slovenian league - match: NK Domzale - NK Celje</title>
  </programme>
  <programme channel="Sportklub.HD.pl" start="20251128030500 -0600" stop="20251128051500 -0600">
    <title lang="pl">Football: Greek League - match: Asteras Tripolis - Panetolikos GFS</title>
  </programme>
  <programme channel="Sportklub.HD.pl" start="20251128051500 -0600" stop="20251128072500 -0600">
    <title lang="pl">Women's volleyball: Slovenian league - match: OTP Banka Branik Maribor - OK Formis</title>
  </programme>
  <programme channel="Sportklub.HD.pl" start="20251128072500 -0600" stop="20251128093000 -0600">
    <title lang="pl">Men's basketball: Spanish league - match: Valencia Basket - La Laguna Tenerife</title>
  </programme>
  <programme channel="Sportklub.HD.pl" start="20251128093000 -0600" stop="20251128113000 -0600">
    <title lang="pl">Football: Slovenian League - match: NK Maribor - NK Olimpija Ljubljana</title>
  </programme>
  <programme channel="Sportklub.HD.pl" start="20251128113000 -0600" stop="20251128133500 -0600">
    <title lang="pl">Men's basketball: Spanish league - match: Unicaja Malaga - BAXI Manresa</title>
  </programme>
  <programme channel="Sportklub.HD.pl" start="20251128133500 -0600" stop="20251128163000 -0600">
    <title lang="pl">Equestrian: World Cup competitions in Stuttgart</title>
  </programme>
  <programme channel="Sportklub.HD.pl" start="20251128163000 -0600" stop="20251128170000 -0600">
    <title lang="pl">World of Freesports</title>
    <desc lang="pl">Short reports from the most interesting events from the world of extreme sports.</desc>
    <category lang="pl">magazyn sportowy</category>
  </programme>
  <programme channel="Sportklub.HD.pl" start="20251128170000 -0600" stop="20251128192000 -0600">
    <title lang="pl">Women's soccer: National Women's Soccer League - final match</title>
  </programme>
  <programme channel="Sportklub.HD.pl" start="20251128192000 -0600" stop="20251128213500 -0600">
    <title lang="pl">Football: Slovenian league - match: NK Bravo - NK Radomlje</title>
  </programme>
  <programme channel="Sportklub.HD.pl" start="20251128213500 -0600" stop="20251128230000 -0600">
    <title lang="pl">Equestrian: World Cup competitions in Stuttgart - summary</title>
  </programme>
  <programme channel="Sportklub.HD.pl" start="20251128230000 -0600" stop="20251129012000 -0600">
    <title lang="pl">Women's volleyball: Slovenian league - match: OTP Banka Branik Maribor - OK Formis</title>
  </programme>
  <programme channel="Sportklub.pl" start="20251124011500 -0600" stop="20251124035500 -0600">
    <title lang="pl">Men's basketball: Spanish League - match: Casademont Zaragoza - Unicaja Malaga</title>
  </programme>
  <programme channel="Sportklub.pl" start="20251124035500 -0600" stop="20251124061500 -0600">
    <title lang="pl">Football: Slovenian league - match: FC Koper - NK Aluminij</title>
  </programme>
  <programme channel="Sportklub.pl" start="20251124061500 -0600" stop="20251124092000 -0600">
    <title lang="pl">Equestrian: World Cup competitions in Stuttgart</title>
  </programme>
  <programme channel="Sportklub.pl" start="20251124092000 -0600" stop="20251124103000 -0600">
    <title lang="pl">Equestrian: World Cup competitions in Stuttgart - summary</title>
  </programme>
  <programme channel="Sportklub.pl" start="20251124103000 -0600" stop="20251124123000 -0600">
    <title lang="pl">Football: Slovenian league - match: NK Bravo - NK Radomlje</title>
  </programme>
  <programme channel="Sportklub.pl" start="20251124123000 -0600" stop="20251124144000 -0600">
    <title lang="pl">Men's basketball: Spanish league - match: Barca - Cazoo Baskonia Vitoria-Gasteiz</title>
  </programme>
  <programme channel="Sportklub.pl" start="20251124144000 -0600" stop="20251124164500 -0600">
    <title lang="pl">Football: Slovenian league - match: NK Domzale - NK Celje</title>
  </programme>
  <programme channel="Sportklub.pl" start="20251124164500 -0600" stop="20251124193000 -0600">
    <title lang="pl">Men's basketball: Spanish league - match: Unicaja Malaga - BAXI Manresa</title>
  </programme>
  <programme channel="Sportklub.pl" start="20251124193000 -0600" stop="20251124222500 -0600">
    <title lang="pl">Women's soccer: National Women's Soccer League - final match: Washington Spirit - Gotham FC</title>
  </programme>
  <programme channel="Sportklub.pl" start="20251124222500 -0600" stop="20251124230000 -0600">
    <title lang="pl">GWA Wingfoil World Tour</title>
    <category lang="pl">magazyn sportowy</category>
  </programme>
  <programme channel="Sportklub.pl" start="20251124230000 -0600" stop="20251125013000 -0600">
    <title lang="pl">Men's basketball: Spanish league - match: Cazoo Baskonia Vitoria-Gasteiz - Surne Bilbao Basket</title>
  </programme>
  <programme channel="Sportklub.pl" start="20251125013000 -0600" stop="20251125034000 -0600">
    <title lang="pl">Football: Greek League - match: Asteras Tripolis - Panetolikos GFS</title>
  </programme>
  <programme channel="Sportklub.pl" start="20251125034000 -0600" stop="20251125054500 -0600">
    <title lang="pl">Football: Slovenian League - match: NK Maribor - NK Olimpija Ljubljana</title>
  </programme>
  <programme channel="Sportklub.pl" start="20251125054500 -0600" stop="20251125080000 -0600">
    <title lang="pl">Men's basketball: Spanish league - match: CB Gran Canaria - Barca</title>
  </programme>
  <programme channel="Sportklub.pl" start="20251125080000 -0600" stop="20251125101500 -0600">
    <title lang="pl">Football: Greek League - match: MGS Panserraikos - Panathinaikos AO</title>
  </programme>
  <programme channel="Sportklub.pl" start="20251125101500 -0600" stop="20251125121500 -0600">
    <title lang="pl">Football: Slovenian league - match: FC Koper - NK Aluminij</title>
  </programme>
  <programme channel="Sportklub.pl" start="20251125121500 -0600" stop="20251125124000 -0600">
    <title lang="pl">Fifth quarter</title>
    <desc lang="pl">A summary of the most interesting events of the last round in the Spanish basketball league, ACB.</desc>
    <category lang="pl">magazyn sportowy</category>
  </programme>
  <programme channel="Sportklub.pl" start="20251125124000 -0600" stop="20251125153500 -0600">
    <title lang="pl">Equestrian: World Cup competitions in Stuttgart</title>
  </programme>
  <programme channel="Sportklub.pl" start="20251125153500 -0600" stop="20251125170000 -0600">
    <title lang="pl">Women's volleyball: Slovenian league - match: OTP Banka Branik Maribor - OK Formis</title>
  </programme>
  <programme channel="Sportklub.pl" start="20251125170000 -0600" stop="20251125192000 -0600">
    <title lang="pl">Men's basketball: Spanish league - match: Barca - Cazoo Baskonia Vitoria-Gasteiz</title>
  </programme>
  <programme channel="Sportklub.pl" start="20251125192000 -0600" stop="20251125213000 -0600">
    <title lang="pl">Football: Slovenian league - match: NK Domzale - NK Celje</title>
  </programme>
  <programme channel="Sportklub.pl" start="20251125213000 -0600" stop="20251125230000 -0600">
    <title lang="pl">Equestrian: World Cup competitions in Oslo - summary</title>
  </programme>
  <programme channel="Sportklub.pl" start="20251125230000 -0600" stop="20251126013500 -0600">
    <title lang="pl">Men's basketball: Spanish league - match: Cazoo Baskonia Vitoria-Gasteiz - Surne Bilbao Basket</title>
  </programme>
  <programme channel="Sportklub.pl" start="20251126013500 -0600" stop="20251126034500 -0600">
    <title lang="pl">Football: Greek League - match: MGS Panserraikos - Panathinaikos AO</title>
  </programme>
  <programme channel="Sportklub.pl" start="20251126034500 -0600" stop="20251126060000 -0600">
    <title lang="pl">Football: Slovenian league - match: FC Koper - NK Aluminij</title>
  </programme>
  <programme channel="Sportklub.pl" start="20251126060000 -0600" stop="20251126083000 -0600">
    <title lang="pl">Men's basketball: Spanish league - match: Unicaja Malaga - BAXI Manresa</title>
  </programme>
  <programme channel="Sportklub.pl" start="20251126083000 -0600" stop="20251126103500 -0600">
    <title lang="pl">Football: Greek League - match: PAOK FC - AE Kifisia</title>
  </programme>
  <programme channel="Sportklub.pl" start="20251126103500 -0600" stop="20251126123000 -0600">
    <title lang="pl">Football: Slovenian league - match: NK Domzale - NK Celje</title>
  </programme>
  <programme channel="Sportklub.pl" start="20251126123000 -0600" stop="20251126124500 -0600">
    <title lang="pl">Fifth quarter</title>
    <desc lang="pl">A summary of the most interesting events of the last round in the Spanish basketball league, ACB.</desc>
    <category lang="pl">magazyn sportowy</category>
  </programme>
  <programme channel="Sportklub.pl" start="20251126124500 -0600" stop="20251126151000 -0600">
    <title lang="pl">Men's basketball: Spanish league - match: Barca - Cazoo Baskonia Vitoria-Gasteiz</title>
  </programme>
  <programme channel="Sportklub.pl" start="20251126151000 -0600" stop="20251126172000 -0600">
    <title lang="pl">Football: Slovenian League - match: NK Maribor - NK Olimpija Ljubljana</title>
  </programme>
  <programme channel="Sportklub.pl" start="20251126172000 -0600" stop="20251126204000 -0600">
    <title lang="pl">Equestrian: World Cup competitions in Stuttgart</title>
  </programme>
  <programme channel="Sportklub.pl" start="20251126204000 -0600" stop="20251126230000 -0600">
    <title lang="pl">Women's volleyball: Slovenian league - match: OTP Banka Branik Maribor - OK Formis</title>
  </programme>
  <programme channel="Sportklub.pl" start="20251126230000 -0600" stop="20251127020000 -0600">
    <title lang="pl">Equestrian: World Cup competitions in Stuttgart</title>
  </programme>
  <programme channel="Sportklub.pl" start="20251127020000 -0600" stop="20251127040500 -0600">
    <title lang="pl">Football: Slovenian league - match: NK Domzale - NK Celje</title>
  </programme>
  <programme channel="Sportklub.pl" start="20251127040500 -0600" stop="20251127061500 -0600">
    <title lang="pl">Women's soccer: National Women's Soccer League - final match</title>
  </programme>
  <programme channel="Sportklub.pl" start="20251127061500 -0600" stop="20251127082500 -0600">
    <title lang="pl">Men's basketball: Spanish league - match: Unicaja Malaga - BAXI Manresa</title>
  </programme>
  <programme channel="Sportklub.pl" start="20251127082500 -0600" stop="20251127104000 -0600">
    <title lang="pl">Football: Greek League - match: MGS Panserraikos - Panathinaikos AO</title>
  </programme>
  <programme channel="Sportklub.pl" start="20251127104000 -0600" stop="20251127130000 -0600">
    <title lang="pl">Women's volleyball: Slovenian league - match: OTP Banka Branik Maribor - OK Formis</title>
  </programme>
  <programme channel="Sportklub.pl" start="20251127130000 -0600" stop="20251127151500 -0600">
    <title lang="pl">Football: Slovenian league - match: NK Bravo - NK Radomlje</title>
  </programme>
  <programme channel="Sportklub.pl" start="20251127151500 -0600" stop="20251127173500 -0600">
    <title lang="pl">Football: Greek League - match: PAOK FC - AE Kifisia</title>
  </programme>
  <programme channel="Sportklub.pl" start="20251127173500 -0600" stop="20251127195000 -0600">
    <title lang="pl">Men's basketball: Spanish league - match: Valencia Basket - La Laguna Tenerife</title>
  </programme>
  <programme channel="Sportklub.pl" start="20251127195000 -0600" stop="20251127220500 -0600">
    <title lang="pl">Football: Slovenian league - match: FC Koper - NK Aluminij</title>
  </programme>
  <programme channel="Sportklub.pl" start="20251127220500 -0600" stop="20251127230000 -0600">
    <title lang="pl">World of Freesports</title>
    <desc lang="pl">Short reports from the most interesting events from the world of extreme sports.</desc>
    <category lang="pl">magazyn sportowy</category>
  </programme>
  <programme channel="Sportklub.pl" start="20251127230000 -0600" stop="20251128010500 -0600">
    <title lang="pl">Men's basketball: Spanish league - match: CB Gran Canaria - Barca</title>
  </programme>
  <programme channel="Sportklub.pl" start="20251128010500 -0600" stop="20251128030500 -0600">
    <title lang="pl">Football: Slovenian league - match: NK Domzale - NK Celje</title>
  </programme>
  <programme channel="Sportklub.pl" start="20251128030500 -0600" stop="20251128051500 -0600">
    <title lang="pl">Football: Greek League - match: Asteras Tripolis - Panetolikos GFS</title>
  </programme>
  <programme channel="Sportklub.pl" start="20251128051500 -0600" stop="20251128072500 -0600">
    <title lang="pl">Women's volleyball: Slovenian league - match: OTP Banka Branik Maribor - OK Formis</title>
  </programme>
  <programme channel="Sportklub.pl" start="20251128072500 -0600" stop="20251128093000 -0600">
    <title lang="pl">Men's basketball: Spanish league - match: Valencia Basket - La Laguna Tenerife</title>
  </programme>
  <programme channel="Sportklub.pl" start="20251128093000 -0600" stop="20251128113000 -0600">
    <title lang="pl">Football: Slovenian League - match: NK Maribor - NK Olimpija Ljubljana</title>
  </programme>
  <programme channel="Sportklub.pl" start="20251128113000 -0600" stop="20251128133500 -0600">
    <title lang="pl">Men's basketball: Spanish league - match: Unicaja Malaga - BAXI Manresa</title>
  </programme>
  <programme channel="Sportklub.pl" start="20251128133500 -0600" stop="20251128163000 -0600">
    <title lang="pl">Equestrian: World Cup competitions in Stuttgart</title>
  </programme>
  <programme channel="Sportklub.pl" start="20251128163000 -0600" stop="20251128170000 -0600">
    <title lang="pl">World of Freesports</title>
    <desc lang="pl">Short reports from the most interesting events from the world of extreme sports.</desc>
    <category lang="pl">magazyn sportowy</category>
  </programme>
  <programme channel="Sportklub.pl" start="20251128170000 -0600" stop="20251128192000 -0600">
    <title lang="pl">Women's soccer: National Women's Soccer League - final match</title>
  </programme>
  <programme channel="Sportklub.pl" start="20251128192000 -0600" stop="20251128213500 -0600">
    <title lang="pl">Football: Slovenian league - match: NK Bravo - NK Radomlje</title>
  </programme>
  <programme channel="Sportklub.pl" start="20251128213500 -0600" stop="20251128230000 -0600">
    <title lang="pl">Equestrian: World Cup competitions in Stuttgart - summary</title>
  </programme>
  <programme channel="Sportklub.pl" start="20251128230000 -0600" stop="20251129012000 -0600">
    <title lang="pl">Women's volleyball: Slovenian league - match: OTP Banka Branik Maribor - OK Formis</title>
  </programme>
  </tv>